AUTHORS
COPYING
CREDITS
ChangeLog
FAQ
INSTALL
NEWS
README
THANKS
TODO
doap.rdf
setup.py
entwine/__init__.py
entwine/cli.py
entwine/entwinelib.py
entwine/utils.py
entwine.egg-info/PKG-INFO
entwine.egg-info/SOURCES.txt
entwine.egg-info/dependency_links.txt
entwine.egg-info/entry_points.txt
entwine.egg-info/requires.txt
entwine.egg-info/top_level.txt