Metadata-Version: 1.0
Name: entwine
Version: 0.0.1
Summary: Command-line tool querying twine.com
Home-page: http://code.google.com/p/entwine/
Author: Rob Cakebread
Author-email: <cakebread@gmail.com>
License: GPL-2
Keywords: twine,semweb,RDF
Platform: UNKNOWN
Classifier: Development Status :: 3 - Alpha
Classifier: Intended Audience :: Developers
Classifier: License :: OSI Approved :: BSD License
Classifier: Programming Language :: Python
Classifier: Topic :: Software Development :: Libraries :: Python Modules
